baby_steps/__init__.py
baby_steps/_step.py
baby_steps/hooks.py
baby_steps/py.typed
baby_steps-1.3.1.dist-info/LICENSE
baby_steps-1.3.1.dist-info/METADATA
baby_steps-1.3.1.dist-info/WHEEL
baby_steps-1.3.1.dist-info/top_level.txt
baby_steps-1.3.1.dist-info/RECORD
